cloudbeds_accounting/__init__.py
cloudbeds_accounting/api_client.py
cloudbeds_accounting/api_response.py
cloudbeds_accounting/configuration.py
cloudbeds_accounting/exceptions.py
cloudbeds_accounting/py.typed
cloudbeds_accounting/rest.py
cloudbeds_accounting/api/__init__.py
cloudbeds_accounting/api/accounts_receivable_ledger_api.py
cloudbeds_accounting/api/custom_general_ledger_codes_api.py
cloudbeds_accounting/api/custom_transaction_codes_api.py
cloudbeds_accounting/api/deposits_api.py
cloudbeds_accounting/api/internal_transaction_codes_api.py
cloudbeds_accounting/api/settings_api.py
cloudbeds_accounting/api/source_balance_api.py
cloudbeds_accounting/api/transactions_api.py
cloudbeds_accounting/api/trial_balance_api.py
cloudbeds_accounting/models/__init__.py
cloudbeds_accounting/models/account.py
cloudbeds_accounting/models/account_category.py
cloudbeds_accounting/models/accounts_receivable_ledger_paginated.py
cloudbeds_accounting/models/accounts_receivable_ledger_patch_request.py
cloudbeds_accounting/models/accounts_receivable_ledger_post_request.py
cloudbeds_accounting/models/accounts_receivable_ledger_reservation_balance_transfer_response.py
cloudbeds_accounting/models/accounts_receivable_ledger_reservation_balance_transfer_response_transaction.py
cloudbeds_accounting/models/accounts_receivable_ledger_response.py
cloudbeds_accounting/models/accounts_receivable_ledger_status.py
cloudbeds_accounting/models/accounts_receivable_ledger_totals_response.py
cloudbeds_accounting/models/action.py
cloudbeds_accounting/models/and_or_group.py
cloudbeds_accounting/models/and_or_group_and_inner.py
cloudbeds_accounting/models/api_accounting_error.py
cloudbeds_accounting/models/api_error_code.py
cloudbeds_accounting/models/async_event_response.py
cloudbeds_accounting/models/balance_breakdown_item.py
cloudbeds_accounting/models/chart_of_account_type.py
cloudbeds_accounting/models/conditional_operator.py
cloudbeds_accounting/models/custom_general_ledger_code_model.py
cloudbeds_accounting-1.5.0.dist-info/licenses/LICENSE
cloudbeds_accounting-1.5.0.dist-info/METADATA
cloudbeds_accounting-1.5.0.dist-info/WHEEL
cloudbeds_accounting-1.5.0.dist-info/top_level.txt
cloudbeds_accounting-1.5.0.dist-info/RECORD
